seek_music/__init__.py
seek_music/_client.py
seek_music/config.py
seek_music/resources/__init__.py
seek_music/resources/kkbox/__init__.py
seek_music/resources/kkbox/_client.py
seek_music/resources/kkbox/albums.py
seek_music/resources/kkbox/artists.py
seek_music/resources/kkbox/charts.py
seek_music/resources/kkbox/children_categories.py
seek_music/resources/kkbox/featured_playlist_categories.py
seek_music/resources/kkbox/featured_playlists.py
seek_music/resources/kkbox/genre_stations.py
seek_music/resources/kkbox/mood_stations.py
seek_music/resources/kkbox/new_hits_playlists.py
seek_music/resources/kkbox/new_release_categories.py
seek_music/resources/kkbox/oauth2.py
seek_music/resources/kkbox/session_playlists.py
seek_music/resources/kkbox/shared_playlists.py
seek_music/resources/kkbox/token.py
seek_music/resources/kkbox/tracks.py
seek_music/types/__init__.py
seek_music/types/kkbox/__init__.py
seek_music/types/kkbox/album.py
seek_music/types/kkbox/album_data.py
seek_music/types/kkbox/artist.py
seek_music/types/kkbox/artist_data.py
seek_music/types/kkbox/category.py
seek_music/types/kkbox/category_data.py
seek_music/types/kkbox/genre.py
seek_music/types/kkbox/genre_data.py
seek_music/types/kkbox/image.py
seek_music/types/kkbox/paging.py
seek_music/types/kkbox/playlist.py
seek_music/types/kkbox/playlist_data.py
seek_music/types/kkbox/search_call.py
seek_music/types/kkbox/search_response.py
seek_music/types/kkbox/summary.py
seek_music/types/kkbox/territory.py
seek_music/types/kkbox/token.py
seek_music/types/kkbox/track.py
seek_music/types/kkbox/track_data.py
seek_music/utils/__init__.py
seek_music/utils/_time.py
seek_music/utils/url.py
seek_music-0.3.0.dist-info/LICENSE
seek_music-0.3.0.dist-info/METADATA
seek_music-0.3.0.dist-info/WHEEL
seek_music-0.3.0.dist-info/RECORD
